{
    "id": "your-environment-id",
    "name": "FocusLife+ Local",
    "values": [
        {
            "key": "baseUrl",
            "value": "https://localhost:7290",
            "type": "string",
            "enabled": true
        },
        {
            "key": "accessToken",
            "value": "",
            "type": "string",
            "enabled": true
        },
        {
            "key": "refreshToken",
            "value": "",
            "type": "string",
            "enabled": true
        },
        {
            "key": "categoryId",
            "value": "",
            "type": "string",
            "enabled": true
        }
    ],
    "_postman_variable_scope": "environment"
} 